{
	"replace": false,
	"values": [
		"minecraft:crafting_table",
		"minecraft:bell",
		{
			"id": "#tombstone:graves",
			"required": false
		},
		{
			"id": "#waystones:waystone",
			"required": false
		},
		{
			"id": "#waystones:sharestone",
			"required": false
		},
		{
			"id": "fwaystones:waystone",
			"required": false
		},
		{
			"id": "fwaystones:desert_waystone",
			"required": false
		},
		{
			"id": "fwaystones:stone_brick_waystone",
			"required": false
		},
		{
			"id": "fwaystones:red_desert_waystone",
			"required": false
		},
		{
			"id": "fwaystones:nether_brick_waystone",
			"required": false
		},
		{
			"id": "fwaystones:red_nether_brick_waystone",
			"required": false
		},
		{
			"id": "fwaystones:end_stone_brick_waystone",
			"required": false
		},
		{
			"id": "fwaystones:deepslate_brick_waystone",
			"required": false
		},
		{
			"id": "fwaystones:blackstone_brick_waystone",
			"required": false
		},
		{
			"id": "lightmanscurrency:atm",
			"required": false
		},
		{
			"id": "lightmanscurrency:paygate",
			"required": false
		},
		{
			"id": "lightmanscurrency:ticket_machine",
			"required": false
		},
		{
			"id": "lightmanscurrency:shelf_oak",
			"required": false
		},
		{
			"id": "lightmanscurrency:shelf_birch",
			"required": false
		},
		{
			"id": "lightmanscurrency:shelf_spruce",
			"required": false
		},
		{
			"id": "lightmanscurrency:shelf_jungle",
			"required": false
		},
		{
			"id": "lightmanscurrency:shelf_acacia",
			"required": false
		},
		{
			"id": "lightmanscurrency:shelf_dark_oak",
			"required": false
		},
		{
			"id": "lightmanscurrency:shelf_crimson",
			"required": false
		},
		{
			"id": "lightmanscurrency:shelf_warped",
			"required": false
		},
		{
			"id": "lightmanscurrency:display_case",
			"required": false
		},
		{
			"id": "lightmanscurrency:armor_display",
			"required": false
		},
		{
			"id": "lightmanscurrency:freezer",
			"required": false
		},
		{
			"id": "lightmanscurrency:freezer",
			"required": false
		},
		{
			"id": "lightmanscurrency:card_display_oak",
			"required": false
		},
		{
			"id": "lightmanscurrency:card_display_birch",
			"required": false
		},
		{
			"id": "lightmanscurrency:card_display_spruce",
			"required": false
		},
		{
			"id": "lightmanscurrency:card_display_jungle",
			"required": false
		},
		{
			"id": "lightmanscurrency:card_display_acacia",
			"required": false
		},
		{
			"id": "lightmanscurrency:card_display_dark_oak",
			"required": false
		},
		{
			"id": "lightmanscurrency:card_display_crimson",
			"required": false
		},
		{
			"id": "lightmanscurrency:card_display_warped",
			"required": false
		},
		{
			"id": "lightmanscurrency:vending_machine",
			"required": false
		},
		{
			"id": "lightmanscurrency:vending_machine_red",
			"required": false
		},
		{
			"id": "lightmanscurrency:vending_machine_blue",
			"required": false
		},
		{
			"id": "lightmanscurrency:vending_machine_green",
			"required": false
		},
		{
			"id": "lightmanscurrency:vending_machine_pink",
			"required": false
		},
		{
			"id": "lightmanscurrency:vending_machine_lightblue",
			"required": false
		},
		{
			"id": "lightmanscurrency:vending_machine_lime",
			"required": false
		},
		{
			"id": "lightmanscurrency:vending_machine_yellow",
			"required": false
		},
		{
			"id": "lightmanscurrency:vending_machine_black",
			"required": false
		},
		{
			"id": "lightmanscurrency:vending_machine_large",
			"required": false
		},
		{
			"id": "lightmanscurrency:vending_machine_large_red",
			"required": false
		},
		{
			"id": "lightmanscurrency:vending_machine_large_blue",
			"required": false
		},
		{
			"id": "lightmanscurrency:vending_machine_large_green",
			"required": false
		},
		{
			"id": "lightmanscurrency:vending_machine_large_pink",
			"required": false
		},
		{
			"id": "lightmanscurrency:vending_machine_large_lightblue",
			"required": false
		},
		{
			"id": "lightmanscurrency:vending_machine_large_lime",
			"required": false
		},
		{
			"id": "lightmanscurrency:vending_machine_large_yellow",
			"required": false
		},
		{
			"id": "lightmanscurrency:vending_machine_large_black",
			"required": false
		},
		{
			"id": "lightmanscurrency:item_trader_server_sml",
			"required": false
		},
		{
			"id": "lightmanscurrency:item_trader_server_med",
			"required": false
		},
		{
			"id": "lightmanscurrency:item_trader_server_lrg",
			"required": false
		},
		{
			"id": "lightmanscurrency:item_trader_server_xlrg",
			"required": false
		}
	]
}
